pytdi/__init__.py
pytdi/core.py
pytdi/dsp.py
pytdi/interface.py
pytdi/intervar.py
pytdi/michelson.py
pytdi/naming.py
pytdi/ortho.py
pytdi/sagnac.py
pytdi-2.1.0.dist-info/METADATA
pytdi-2.1.0.dist-info/WHEEL
pytdi-2.1.0.dist-info/licenses/LICENSE
pytdi-2.1.0.dist-info/RECORD
