Metadata-Version: 2.4
Name: pytdi
Version: 2.1.0
Summary: Manipulate and evaluate time-delay interferometry combinations.
Project-URL: Documentation, https://lisa.pages.in2p3.fr/LDPG/wg6_inrep/pytdi
Project-URL: Repository, https://gitlab.in2p3.fr/LISA/LDPG/wg6_inrep/pytdi
Project-URL: Issues, https://gitlab.in2p3.fr/LISA/LDPG/wg6_inrep/pytdi/-/issues
Author-email: Martin Staab <martin.staab@aei.mpg.de>, Jean-Baptiste Bayle <j2b.bayle@gmail.com>, Olaf Hartwig <olaf.hartwig@aei.mpg.de>
Maintainer-email: Martin Staab <martin.staab@aei.mpg.de>, Jean-Baptiste Bayle <j2b.bayle@gmail.com>, Olaf Hartwig <olaf.hartwig@aei.mpg.de>
License: BSD-3-Clause
License-File: LICENSE
Keywords: INREP,L01,LISA,calibration,noise reduction,pre-processing
Classifier: Intended Audience :: Science/Research
Classifier: Topic :: Scientific/Engineering :: Astronomy
Classifier: Topic :: Scientific/Engineering :: Physics
Requires-Python: >=3.11
Requires-Dist: h5py>=3.1.0
Requires-Dist: numpy>=1.19.5
Requires-Dist: scipy>=1.16.1
Provides-Extra: lisainstrument
Requires-Dist: lisainstrument>=1.0.0; extra == 'lisainstrument'
